__init__.py
blest.py
blest-1.0.3.dist-info/LICENSE
blest-1.0.3.dist-info/METADATA
blest-1.0.3.dist-info/WHEEL
blest-1.0.3.dist-info/top_level.txt
blest-1.0.3.dist-info/RECORD
