Metadata-Version: 2.1
Name: blest
Version: 1.0.3
Summary: The Python reference implementation of BLEST (Batch-able, Lightweight, Encrypted State Transfer), an improved communication protocol for web APIs which leverages JSON, supports request batching by default, and provides a modern alternative to REST.
Home-page: https://blest.jhunt.dev
Author: JHunt
Author-email: hello@jhunt.dev
License: MIT
Platform: any
Classifier: Intended Audience :: Developers
Classifier: Topic :: Software Development :: Libraries
Classifier: Programming Language :: Python :: 3
Classifier: License :: OSI Approved :: MIT License
Classifier: Operating System :: OS Independent
Requires-Python: >=3.8
License-File: LICENSE
Requires-Dist: aiohttp
